Semaphore/Configuration.py
Semaphore/__init__.py
Semaphore/API/Base.py
Semaphore/API/__init__.py
Semaphore/API/v1/Semaphore.py
Semaphore/API/v1/Service.py
Semaphore/API/v1/__init__.py
Semaphore_Microservice-0.1.1.dist-info/LICENSE.md
Semaphore_Microservice-0.1.1.dist-info/METADATA
Semaphore_Microservice-0.1.1.dist-info/WHEEL
Semaphore_Microservice-0.1.1.dist-info/top_level.txt
Semaphore_Microservice-0.1.1.dist-info/RECORD
