Metadata-Version: 2.1
Name: Semaphore-Microservice
Version: 0.1.1
Summary: A HTTP-based microservice offering a ReST API to acquire and release resources that are limited with a semaphore semantic.
Home-page: https://github.com/Paebbels/Semaphore-Microservice
Author: Patrick Lehmann
Author-email: Paebbels@gmail.com
License: UNKNOWN
Project-URL: Documentation, https://Semaphore-Microservice.readthedocs.io/en/latest/
Project-URL: Source Code, https://github.com/Paebbels/Semaphore-Microservice
Project-URL: Issue Tracker, https://github.com/Paebbels/Semaphore-Microservice/issues
Keywords: Python3 Exceptions
Platform: UNKNOWN
Classifier: License :: OSI Approved :: Apache Software License
Classifier: Operating System :: OS Independent
Classifier: Programming Language :: Python :: 3 :: Only
Classifier: Programming Language :: Python :: 3.5
Classifier: Programming Language :: Python :: 3.6
Classifier: Programming Language :: Python :: 3.7
Classifier: Programming Language :: Python :: 3.8
Classifier: Development Status :: 2 - Pre-Alpha
Classifier: Topic :: Internet :: WWW/HTTP :: HTTP Servers
Requires-Python: >=3.5
Requires-Dist: ruamel.yaml
Requires-Dist: py-flags
Requires-Dist: pyAttributes
Requires-Dist: pyExceptions
Requires-Dist: pyGenericPath
Requires-Dist: pyHTTPInterface
Requires-Dist: pyHTTPServer
Requires-Dist: pyHTTPRequestRouter
Requires-Dist: SphinxExtensions
